icesat2waves/__init__.py
icesat2waves/app.py
icesat2waves/clitools.py
icesat2waves/analysis_db/A02c_IOWAGA_thredds_prior.py
icesat2waves/analysis_db/B01_SL_load_single_file.py
icesat2waves/analysis_db/B02_make_spectra_gFT.py
icesat2waves/analysis_db/B03_plot_spectra_ov.py
icesat2waves/analysis_db/B04_angle.py
icesat2waves/analysis_db/B05_define_angle.py
icesat2waves/analysis_db/B06_correct_separate_var.py
icesat2waves/analysis_db/__init__.py
icesat2waves/config/__init__.py
icesat2waves/config/color_def.ai
icesat2waves/config/color_def.ase
icesat2waves/config/color_def.json
icesat2waves/config/config.json
icesat2waves/config/generate_colors.py
icesat2waves/config/startup.py
icesat2waves/local_modules/__init__.py
icesat2waves/local_modules/jonswap_gamma.py
icesat2waves/local_modules/m_colormanager_ph3.py
icesat2waves/local_modules/m_general_ph3.py
icesat2waves/local_modules/m_spectrum_ph3.py
icesat2waves/local_modules/m_tools_ph3.py
icesat2waves/tools/__init__.py
icesat2waves/tools/angle_optimizer.py
icesat2waves/tools/beam_stats.py
icesat2waves/tools/convert_GPS_time.py
icesat2waves/tools/convert_julian.py
icesat2waves/tools/filter_regrid.py
icesat2waves/tools/generalized_FT.py
icesat2waves/tools/iotools.py
icesat2waves/tools/lanczos.py
icesat2waves/tools/read_ground_tracks.py
icesat2waves/tools/sliderule_converter_tools.py
icesat2waves/tools/spectral_estimates.py
icesat2waves/tools/spicke_remover.py
icesat2waves/tools/wave_tools.py
icesat2waves-1.0.0.dist-info/LICENSE.txt
icesat2waves-1.0.0.dist-info/METADATA
icesat2waves-1.0.0.dist-info/WHEEL
icesat2waves-1.0.0.dist-info/entry_points.txt
icesat2waves-1.0.0.dist-info/top_level.txt
icesat2waves-1.0.0.dist-info/RECORD
