Metadata-Version: 2.1
Name: icesat2waves
Version: 1.0.0
Summary: Tools to analyze wave tracks using icesat2 data
Author-email: "Momme C. Hell" <momme_hell@brown.edu>
License: GNU GENERAL PUBLIC LICENSE
Project-URL: Homepage, https://github.com/brown-ccv/icesat2waves
Project-URL: Bug Reports, https://github.com/brown-ccv/icesat2waves/issues
Project-URL: Source, https://github.com/brown-ccv/icesat2waves
Keywords: earth observation,icesat2
Classifier: Development Status :: 3 - Alpha
Classifier: Intended Audience :: Science/Research
Classifier: Topic :: Scientific/Engineering :: GIS
Classifier: Programming Language :: Python :: 3.10
Classifier: Programming Language :: Python :: 3.11
Classifier: Programming Language :: Python :: 3 :: Only
Requires-Python: >=3.10
License-File: LICENSE.txt
Requires-Dist: piecewise-regression <2.0.0,>=1.3.0
Requires-Dist: numba <1.0.0,>=0.58.1
Requires-Dist: xarray >=2024.1.0
Requires-Dist: mpi4py <4.0.0,>=3.1.4
Requires-Dist: numpy <2.0.0,>=1.26.3
Requires-Dist: icesat2-toolkit <2.0.0,>=1.0.0.22
Requires-Dist: pandas <3.0.0,>=2.2.0
Requires-Dist: geopandas <1.0.0,>=0.14.2
Requires-Dist: sliderule <5.0.0,>=4.2.3
Requires-Dist: ipyleaflet <0.19.0,>=0.18.1
Requires-Dist: lmfit <2.0.0,>=1.2.2
Requires-Dist: tables <4.0.0,>=3.9.2
Requires-Dist: emcee <4.0.0,>=3.1.4
Requires-Dist: netCDF4 <2.0.0,>=1.6.5
Requires-Dist: siphon <1.0.0,>=0.9
Requires-Dist: h5py <4.0.0,>=3.5.0
Requires-Dist: termcolor <3.0.0,>=2.4.0
Requires-Dist: typer <1.0.0,>=0.9.0
Requires-Dist: getmem <=1.0.0,>=1.0
Requires-Dist: astropy <=6.0.0,>=5.2
Provides-Extra: dev
Requires-Dist: check-manifest ; extra == 'dev'
Requires-Dist: black ; extra == 'dev'
Requires-Dist: icesat2waves[test] ; extra == 'dev'
Provides-Extra: test
Requires-Dist: coverage ; extra == 'test'
Requires-Dist: pytest <8.0.0,>=7.4.4 ; extra == 'test'
Requires-Dist: pytest-xdist <4.0.0,>=3.5.0 ; extra == 'test'
